telegram_news/__init__.py
telegram_news/constant.py
telegram_news/displaypolicy.py
telegram_news/ratelimit.py
telegram_news/table.sql
telegram_news/utils.py
telegram_news/template/__init__.py
telegram_news/template/common.py
telegram_news-0.5.3.dist-info/LICENSE
telegram_news-0.5.3.dist-info/METADATA
telegram_news-0.5.3.dist-info/WHEEL
telegram_news-0.5.3.dist-info/top_level.txt
telegram_news-0.5.3.dist-info/RECORD
