Metadata-Version: 2.1
Name: telegram-news
Version: 0.5.3
Summary: Python package for automatically fetching and pushing news by Telegram.
Home-page: https://github.com/ESWZY/telegram-news
Author: ESWZY
Author-email: 0903wzy@gmail.com
License: MIT
Platform: UNKNOWN
Classifier: Development Status :: 3 - Alpha
Classifier: License :: OSI Approved :: MIT License
Classifier: Operating System :: OS Independent
Classifier: Programming Language :: Python :: 3.5
Classifier: Programming Language :: Python :: 3.6
Classifier: Programming Language :: Python :: 3.7
Classifier: Programming Language :: Python :: 3.8
Classifier: Intended Audience :: Developers
Classifier: Topic :: Education
Classifier: Topic :: Office/Business :: News/Diary
Classifier: Topic :: Software Development :: Libraries :: Python Modules
Requires-Python: >=3.5
License-File: LICENSE
Requires-Dist: requests
Requires-Dist: SQLAlchemy
Requires-Dist: beautifulsoup4
Requires-Dist: psycopg2
Requires-Dist: lxml
Requires-Dist: xmltodict
